MANIFEST.in
README.md
setup.py
micropython_phew.egg-info/PKG-INFO
micropython_phew.egg-info/SOURCES.txt
micropython_phew.egg-info/dependency_links.txt
micropython_phew.egg-info/top_level.txt
phew/__init__.py
phew/dns.py
phew/logging.py
phew/ntp.py
phew/server.py
phew/template.py