Metadata-Version: 2.1
Name: micropython-phew
Version: 0.0.3
Summary: A small webserver and templating library specifically designed for MicroPython on the Pico W.
Home-page: UNKNOWN
Author: Jonathan Williamson
Maintainer: Phil Howard
Maintainer-email: phil@pimoroni.com
License: MIT
Project-URL: GitHub, https://github.com/pimoroni/phew
Platform: UNKNOWN
